salal/__init__.py
salal/__main__.py
salal/config/system_config.json
salal/core/__init__.py
salal/core/actions.py
salal/core/config.py
salal/core/dependencies.py
salal/core/file_processing.py
salal/core/handlers.py
salal/core/logging.py
salal/core/utilities.py
salal/core/variable_tracker.py
salal/extensions/commands/build/handler.py
salal/extensions/file_processing/copying/handler.py
salal/extensions/file_processing/simple_expansion/handler.py
salal/extensions/file_processing/xml/custom_jinja_functions.py
salal/extensions/file_processing/xml/handler.py
salal-0.27.0b0.dist-info/LICENSE
salal-0.27.0b0.dist-info/METADATA
salal-0.27.0b0.dist-info/WHEEL
salal-0.27.0b0.dist-info/top_level.txt
salal-0.27.0b0.dist-info/RECORD
