Metadata-Version: 2.1
Name: salal
Version: 0.27.0b0
Summary: A system for building websites from templates and content
Home-page: https://github.com/haskelt/salal
Author: Todd Haskell
Author-email: todd@craggypeak.com
License: GNU General Public License v3
Platform: UNKNOWN
Classifier: Programming Language :: Python :: 3
Classifier: License :: OSI Approved :: GNU General Public License v3 (GPLv3)
Classifier: Operating System :: OS Independent
Classifier: Intended Audience :: Developers
Classifier: Topic :: Text Processing :: Markup :: HTML
Requires-Python: >=3.6
Requires-Dist: Jinja2 (>=2.11.2)
